zbdpay/__init__.py
zbdpay/_base_client.py
zbdpay/_client.py
zbdpay/_compat.py
zbdpay/_constants.py
zbdpay/_exceptions.py
zbdpay/_files.py
zbdpay/_models.py
zbdpay/_qs.py
zbdpay/_resource.py
zbdpay/_response.py
zbdpay/_streaming.py
zbdpay/_types.py
zbdpay/_version.py
zbdpay/py.typed
zbdpay/_utils/__init__.py
zbdpay/_utils/_logs.py
zbdpay/_utils/_proxy.py
zbdpay/_utils/_reflection.py
zbdpay/_utils/_resources_proxy.py
zbdpay/_utils/_streams.py
zbdpay/_utils/_sync.py
zbdpay/_utils/_transform.py
zbdpay/_utils/_typing.py
zbdpay/_utils/_utils.py
zbdpay/lib/.keep
zbdpay/resources/__init__.py
zbdpay/resources/email_payments.py
zbdpay/resources/gamertags.py
zbdpay/resources/internal_transfer.py
zbdpay/resources/keysend_payments.py
zbdpay/resources/lightning_address.py
zbdpay/resources/lightning_charges.py
zbdpay/resources/lightning_payments.py
zbdpay/resources/lightning_static_charges.py
zbdpay/resources/oauth2.py
zbdpay/resources/utils.py
zbdpay/resources/vouchers.py
zbdpay/resources/wallet.py
zbdpay/resources/withdrawal_requests.py
zbdpay/types/__init__.py
zbdpay/types/email_payment_send_params.py
zbdpay/types/gamertag_create_charge_params.py
zbdpay/types/gamertag_send_payment_params.py
zbdpay/types/internal_transfer_initiate_params.py
zbdpay/types/keysend_payment_send_params.py
zbdpay/types/lightning_address_create_charge_params.py
zbdpay/types/lightning_address_send_payment_params.py
zbdpay/types/lightning_charge_create_params.py
zbdpay/types/lightning_payment_send_params.py
zbdpay/types/lightning_static_charge_create_params.py
zbdpay/types/lightning_static_charge_update_params.py
zbdpay/types/util_decode_lightning_charge_params.py
zbdpay/types/voucher_create_params.py
zbdpay/types/voucher_redeem_params.py
zbdpay/types/voucher_revoke_params.py
zbdpay/types/withdrawal_request_create_params.py
zbdpay-0.1.0a1.dist-info/METADATA
zbdpay-0.1.0a1.dist-info/WHEEL
zbdpay-0.1.0a1.dist-info/licenses/LICENSE
zbdpay-0.1.0a1.dist-info/RECORD
